chatql/__init__.py
chatql/chatql.py
chatql/engine.py
chatql/matcher/__init__.py
chatql/matcher/regex_matcher.py
chatql/mongodb_client.py
chatql-0.1.1.dist-info/LICENSE
chatql-0.1.1.dist-info/WHEEL
chatql-0.1.1.dist-info/METADATA
chatql-0.1.1.dist-info/RECORD
