Metadata-Version: 2.1
Name: chatql
Version: 0.1.1
Summary: 
Home-page: https://github.com/katsugeneration
License: UNKNOWN
Author: katsugeneration
Author-email: katsu.generation.888@gmail.com
Requires-Python: >=3.6,<4.0
Classifier: Programming Language :: Python :: 3
Classifier: Programming Language :: Python :: 3.6
Classifier: Programming Language :: Python :: 3.7
Requires-Dist: flask[server] (>=1.0,<2.0)
Requires-Dist: graphene (>=2.1,<3.0)
Requires-Dist: line-bot-sdk[line] (>=1.8,<2.0)
Requires-Dist: mongoengine (>=0.16.3,<0.17.0)
Project-URL: Repository, https://github.com/katsugeneration/chatql
